verilog/mux_8_1/mux_8_1.v
module mux_8_1
    (output reg f,
    input [2:0] sel,
    input [7:0] i);

    always @(*)
        begin
            case(sel)
                3'b000 : f = i[0];
                3'b001 : f = i[1];
                3'b010 : f = i[2];
                3'b011 : f = i[3];
                3'b100 : f = i[4];
                3'b101 : f = i[5];
                3'b110 : f = i[6];
                3'b111 : f = i[7];
            endcase
        end
endmodule

verilog/counter_3bit/counter_3bit.v
module counter_3bit
    (output reg[2:0] ctr = 0,
    input clk,
    input rst);

    always @(posedge clk, posedge rst)
        begin
            if (rst)
                ctr <= 0;
            else
                ctr <= ctr + 1;
        end 

endmodule

verilog/sequential_select/sequential_select.v
module sequential_select
    (output out,
    input start,
    input master_rst,
    input [7:0] mux_in,
    input clk);

    wire start_up;
    wire rst;
    wire [2:0] ctr_out;
    wire [2:0] sel;

    assign start_up = start & clk;
    assign sel[2] = ~ctr_out[2] & ~ctr_out[1];
    assign sel[1] = ctr_out[1];
    assign sel[0] = ~ctr_out[0];
    assign rst = start & (master_rst | (ctr_out[2] & ~ctr_out[1] & ctr_out[0]));

    counter_3bit ctr_unit (
        .clk(start_up),
        .rst(rst),
        .ctr(ctr_out)
    );

    mux_8_1 mux_unit (
        .f(out),
        .sel(sel),
        .i(mux_in)
    );
endmodule

verilog/sequential_select/tb_sequential_select.v
module tb_sequential_select;

    reg clk, master_rst, start;
    reg [7:0] mux_in;
    wire out;

    sequential_select uut (
        .out(out),
        .start(start),
        .master_rst(master_rst),
        .mux_in(mux_in),
        .clk(clk)
    );
    
    initial 
        begin
            $dumpfile("tb_sequential_select.vcd");
            $dumpvars(0, tb_sequential_select);
            #5 clk = 0; mux_in = 8'b1010_1010; start = 1; 
            #5 master_rst = 1;
            #25 master_rst = 0;
            #2000 start = 0;
            #965 $finish;
        end 

    always
        #50 clk = ~clk;

endmodule

verilog/sequential_select/tb_sequential_select.vcd
$date
	Thu Dec 18 11:18:21 2025
$end
$version
	Icarus Verilog
$end
$timescale
	1s
$end
$scope module tb_sequential_select $end
$var wire 1 ! out $end
$var reg 1 " clk $end
$var reg 1 # master_rst $end
$var reg 8 $ mux_in [7:0] $end
$var reg 1 % start $end
$scope module uut $end
$var wire 1 " clk $end
$var wire 1 # master_rst $end
$var wire 8 & mux_in [7:0] $end
$var wire 1 ' rst $end
$var wire 1 % start $end
$var wire 1 ( start_up $end
$var wire 3 ) sel [2:0] $end
$var wire 1 ! out $end
$var wire 3 * ctr_out [2:0] $end
$scope module ctr_unit $end
$var wire 1 ( clk $end
$var wire 1 ' rst $end
$var reg 3 + ctr [2:0] $end
$upscope $end
$scope module mux_unit $end
$var wire 8 , i [7:0] $end
$var wire 3 - sel [2:0] $end
$var reg 1 ! f $end
$upscope $end
$upscope $end
$upscope $end
$enddefinitions $end
#0
$dumpvars
b101 -
bx ,
b0 +
b0 *
b101 )
x(
x'
bx &
x%
bx $
x#
x"
x!
$end
#5
1!
0(
1%
b10101010 $
b10101010 &
b10101010 ,
0"
#10
1'
1#
#35
0'
0#
#50
0!
b100 )
b100 -
b1 *
b1 +
1(
1"
#100
0(
0"
#150
1!
b11 )
b11 -
b10 *
b10 +
1(
1"
#200
0(
0"
#250
0!
b10 )
b10 -
b11 *
b11 +
1(
1"
#300
0(
0"
#350
1!
b1 )
b1 -
b100 *
b100 +
1(
1"
#400
0(
0"
#450
0'
1!
b101 )
b101 -
b0 *
b0 +
1(
1"
#500
0(
0"
#550
0!
b100 )
b100 -
b1 *
b1 +
1(
1"
#600
0(
0"
#650
1!
b11 )
b11 -
b10 *
b10 +
1(
1"
#700
0(
0"
#750
0!
b10 )
b10 -
b11 *
b11 +
1(
1"
#800
0(
0"
#850
1!
b1 )
b1 -
b100 *
b100 +
1(
1"
#900
0(
0"
#950
0'
1!
b101 )
b101 -
b0 *
b0 +
1(
1"
#1000
0(
0"
#1050
0!
b100 )
b100 -
b1 *
b1 +
1(
1"
#1100
0(
0"
#1150
1!
b11 )
b11 -
b10 *
b10 +
1(
1"
#1200
0(
0"
#1250
0!
b10 )
b10 -
b11 *
b11 +
1(
1"
#1300
0(
0"
#1350
1!
b1 )
b1 -
b100 *
b100 +
1(
1"
#1400
0(
0"
#1450
0'
1!
b101 )
b101 -
b0 *
b0 +
1(
1"
#1500
0(
0"
#1550
0!
b100 )
b100 -
b1 *
b1 +
1(
1"
#1600
0(
0"
#1650
1!
b11 )
b11 -
b10 *
b10 +
1(
1"
#1700
0(
0"
#1750
0!
b10 )
b10 -
b11 *
b11 +
1(
1"
#1800
0(
0"
#1850
1!
b1 )
b1 -
b100 *
b100 +
1(
1"
#1900
0(
0"
#1950
0'
1!
b101 )
b101 -
b0 *
b0 +
1(
1"
#2000
0(
0"
#2035
0%
